setup.py
src/__init__.py
src/test_dan.py
src/examples/__init__.py
src/examples/from_profile.py
src/examples/get.py
src/examples/poll_status.py
src/examples/post_process.py
src/examples/to_s3_cross_account.py
src/pymental/__init__.py
src/pymental/client.py
src/pymental/endpoints.py
src/pymental/errors.py
src/pymental/fields.py
src/pymental/meta.py
src/pymental.egg-info/PKG-INFO
src/pymental.egg-info/SOURCES.txt
src/pymental.egg-info/dependency_links.txt
src/pymental.egg-info/not-zip-safe
src/pymental.egg-info/requires.txt
src/pymental.egg-info/top_level.txt
src/pymental/models/__init__.py
src/pymental/models/audit.py
src/pymental/models/cloud_config.py
src/pymental/models/content_duration.py
src/pymental/models/error.py
src/pymental/models/group_settings.py
src/pymental/models/input.py
src/pymental/models/job.py
src/pymental/models/location.py
src/pymental/models/node.py
src/pymental/models/notification.py
src/pymental/models/output.py
src/pymental/models/process.py
src/pymental/models/status.py
src/pymental/models/stream_assembly.py
src/pymental/models/timecode_config.py