Metadata-Version: 1.1
Name: pymental
Version: 0.0.6
Summary: Client library for interacting with Elemental Conductor
Home-page: https://github.com/pbs/pymental
Author: PBS Core Services Team
Author-email: pbsi-team-core-services@pbs.org
License: MIT
Keywords: pymental elemental conductor client
Platform: UNKNOWN
Classifier: Development Status :: 3 - Alpha
